pythio/__init__.py
pythio/client.py
pythio/exceptions.py
pythio/fun.py
pythio/network.py
pythio/setup.py
pythio/util.py
pythio-0.0.2.dist-info/LICENSE
pythio-0.0.2.dist-info/METADATA
pythio-0.0.2.dist-info/WHEEL
pythio-0.0.2.dist-info/top_level.txt
pythio-0.0.2.dist-info/RECORD
