Metadata-Version: 2.1
Name: pythio
Version: 0.0.2
Summary: A library for bot development in Telegram messengers
Author-email: amirali irvany <dev.amirali.irvany@gmail.com>
Project-URL: Homepage, https://github.com/metect/pythio
Project-URL: Issues, https://github.com/metect/pythio/issues
Classifier: Programming Language :: Python :: 3
Classifier: License :: OSI Approved :: MIT License
Classifier: Operating System :: OS Independent
Requires-Python: >=3.8
License-File: LICENSE
